<?xml version = '1.0' encoding = 'UTF-8'?>
<Relation class="oracle.dbtools.crest.model.design.logical.Relation" name="fk_patient_patient_temp" directorySegmentName="seg_0" id="A954DF02-9591-69D8-6A29-96C17908272A">
<createdBy>wujf</createdBy>
<createdTime>2012-05-03 06:15:12 UTC</createdTime>
<generatorID>用户生成</generatorID>
<ownerDesignName>CDR</ownerDesignName>
<sourcePk>A613CF4D-8FB9-804F-42C9-0FABD8118736</sourcePk>
<identifying>false</identifying>
<optionalSource>true</optionalSource>
<optionalTarget>false</optionalTarget>
<sourceCardinality>1</sourceCardinality>
<sourceEntity>32112973-C793-E61C-F90E-EC05A5B1900D</sourceEntity>
<targetCardinalityString>*</targetCardinalityString>
<targetEntity>B646B968-502C-1BC7-78CB-0132B72350C1</targetEntity>
<transferable>true</transferable>
</Relation>