<?xml version = '1.0' encoding = 'UTF-8'?>
<Table class="oracle.dbtools.crest.model.design.relational.Table" id="32799B3E-7665-AC85-2ADB-818CF13A4068" directorySegmentName="seg_0" name="transfer_history">
   <createdBy>xu_dengfeng</createdBy>
   <createdTime>2012-02-14 03:28:28 UTC</createdTime>
   <generatorID>7B328BC6-E0BB-5E2B-C25B-1EFE8A829F2F</generatorID>
   <ownerDesignName>CDR</ownerDesignName>
   <engineerTo>
      <item key="C569ACD5-9D32-D25B-CB96-FE071904E1B3" value="true"/>
   </engineerTo>
   <pkName>pk_transfer_history</pkName>
   <fonts>
      <FontObject class="oracle.dbtools.crest.model.design.FontObjectWr">
         <foType>标题</foType>
         <fontStyle>1</fontStyle>
         <colorRGB>-16776961</colorRGB>
      </FontObject>
      <FontObject class="oracle.dbtools.crest.model.design.FontObjectWr">
         <foType>列</foType>
         <colorRGB>-16777216</colorRGB>
      </FontObject>
      <FontObject class="oracle.dbtools.crest.model.design.FontObjectWr">
         <foType>数据类型</foType>
         <colorRGB>-16744448</colorRGB>
      </FontObject>
      <FontObject class="oracle.dbtools.crest.model.design.FontObjectWr">
         <foType>PK 元素</foType>
         <colorRGB>-16776961</colorRGB>
      </FontObject>
      <FontObject class="oracle.dbtools.crest.model.design.FontObjectWr">
         <foType>FK 元素</foType>
         <colorRGB>-16777216</colorRGB>
      </FontObject>
      <FontObject class="oracle.dbtools.crest.model.design.FontObjectWr">
         <foType>UK 元素</foType>
         <colorRGB>-16776961</colorRGB>
      </FontObject>
      <FontObject class="oracle.dbtools.crest.model.design.FontObjectWr">
         <foType>非空值</foType>
         <colorRGB>-65536</colorRGB>
      </FontObject>
      <FontObject class="oracle.dbtools.crest.model.design.FontObjectWr">
         <foType>关键字</foType>
         <colorRGB>-16777216</colorRGB>
      </FontObject>
   </fonts>
   <columns>
      <Column class="oracle.dbtools.crest.model.design.relational.Column" name="transfer_sn" id="083EE24F-9894-D5E7-E2DC-CE9E52386E2D">
         <createdBy>xu_dengfeng</createdBy>
         <createdTime>2012-02-14 03:28:28 UTC</createdTime>
         <generatorID>01FC76B3-244F-42A6-5DDC-471A2E537BBC</generatorID>
         <ownerDesignName>CDR</ownerDesignName>
         <engineerTo>
            <item key="C569ACD5-9D32-D25B-CB96-FE071904E1B3" value="true"/>
         </engineerTo>
         <use>1</use>
         <logicalDatatype>LOGDT011</logicalDatatype>
         <previousColumn>false</previousColumn>
         <autoIncrementCycle>false</autoIncrementCycle>
      </Column>
      <Column class="oracle.dbtools.crest.model.design.relational.Column" name="visit_id" id="568FACA2-BF86-CDBD-5FB1-1B45D1F8367B">
         <createdBy>xu_dengfeng</createdBy>
         <createdTime>2012-02-14 03:28:28 UTC</createdTime>
         <generatorID>4A24D8E6-35AC-9A83-79C9-2C0709744F01</generatorID>
         <ownerDesignName>CDR</ownerDesignName>
         <engineerTo>
            <item key="C569ACD5-9D32-D25B-CB96-FE071904E1B3" value="true"/>
         </engineerTo>
         <use>1</use>
         <logicalDatatype>LOGDT011</logicalDatatype>
         <delegate>1E2D9950-3D6B-8BBD-DF73-685364EC879F</delegate>
         <previousColumn>false</previousColumn>
         <autoIncrementCycle>false</autoIncrementCycle>
         <associations>
            <colAssociation fkAssociation="14A8126E-44A8-E370-A464-3EA0433856B7" referredColumn="1E2D9950-3D6B-8BBD-DF73-685364EC879F"/>
         </associations>
      </Column>
      <Column class="oracle.dbtools.crest.model.design.relational.Column" name="patient_sn" id="2F343DAB-4514-4F46-FFCA-B570F0122006">
         <createdBy>xu_dengfeng</createdBy>
         <createdTime>2012-02-14 03:28:28 UTC</createdTime>
         <generatorID>65994110-E6FA-2C13-4D91-AD066CB23A86</generatorID>
         <ownerDesignName>CDR</ownerDesignName>
         <engineerTo>
            <item key="C569ACD5-9D32-D25B-CB96-FE071904E1B3" value="true"/>
         </engineerTo>
         <use>1</use>
         <logicalDatatype>LOGDT024</logicalDatatype>
         <dataTypeSize>32</dataTypeSize>
         <previousColumn>false</previousColumn>
         <autoIncrementCycle>false</autoIncrementCycle>
      </Column>
      <Column class="oracle.dbtools.crest.model.design.relational.Column" name="patient_domain" id="A5087952-1501-5929-8BB5-410092D8D79B">
         <createdBy>xu_dengfeng</createdBy>
         <createdTime>2012-02-14 03:28:28 UTC</createdTime>
         <generatorID>1FDAA67F-3BF9-00C8-DD49-9E0384ADD0E1</generatorID>
         <ownerDesignName>CDR</ownerDesignName>
         <engineerTo>
            <item key="C569ACD5-9D32-D25B-CB96-FE071904E1B3" value="true"/>
         </engineerTo>
         <use>1</use>
         <logicalDatatype>LOGDT024</logicalDatatype>
         <dataTypeSize>6</dataTypeSize>
         <previousColumn>false</previousColumn>
         <autoIncrementCycle>false</autoIncrementCycle>
      </Column>
      <Column class="oracle.dbtools.crest.model.design.relational.Column" name="patient_lid" id="ADE52A6D-C41B-6F02-16B4-8AC05DD17410">
         <createdBy>xu_dengfeng</createdBy>
         <createdTime>2012-02-14 03:28:28 UTC</createdTime>
         <generatorID>27182638-31D8-AEAB-D709-4204D6C96139</generatorID>
         <ownerDesignName>CDR</ownerDesignName>
         <engineerTo>
            <item key="C569ACD5-9D32-D25B-CB96-FE071904E1B3" value="true"/>
         </engineerTo>
         <use>1</use>
         <logicalDatatype>LOGDT024</logicalDatatype>
         <dataTypeSize>12</dataTypeSize>
         <previousColumn>false</previousColumn>
         <autoIncrementCycle>false</autoIncrementCycle>
      </Column>
      <Column class="oracle.dbtools.crest.model.design.relational.Column" name="医嘱类型" id="5F42CFA9-E973-7F71-2619-3BF9340240C2">
         <createdBy>xu_dengfeng</createdBy>
         <createdTime>2012-02-14 03:28:28 UTC</createdTime>
         <comment>转科&amp;lt;br/&amp;gt;转床&amp;lt;br/&amp;gt;入留观&amp;lt;br/&amp;gt;出留观</comment>
         <generatorID>47D1E878-5459-CA94-F610-500B319FA191</generatorID>
         <ownerDesignName>CDR</ownerDesignName>
         <engineerTo>
            <item key="C569ACD5-9D32-D25B-CB96-FE071904E1B3" value="true"/>
         </engineerTo>
         <use>1</use>
         <logicalDatatype>LOGDT024</logicalDatatype>
         <dataTypeSize>6</dataTypeSize>
         <previousColumn>false</previousColumn>
         <autoIncrementCycle>false</autoIncrementCycle>
      </Column>
      <Column class="oracle.dbtools.crest.model.design.relational.Column" name="order_time" id="5E2DF205-A498-1BC1-91D2-E825013609A2">
         <createdBy>xu_dengfeng</createdBy>
         <createdTime>2012-02-14 03:28:28 UTC</createdTime>
         <comment>开立医嘱的公元纪年日期和时间的完整描述</comment>
         <generatorID>206106F5-8F5A-75D3-C760-5BF961683761</generatorID>
         <ownerDesignName>CDR</ownerDesignName>
         <engineerTo>
            <item key="C569ACD5-9D32-D25B-CB96-FE071904E1B3" value="true"/>
         </engineerTo>
         <nullsAllowed>true</nullsAllowed>
         <use>1</use>
         <logicalDatatype>LOGDT008</logicalDatatype>
         <previousColumn>false</previousColumn>
         <autoIncrementCycle>false</autoIncrementCycle>
      </Column>
      <Column class="oracle.dbtools.crest.model.design.relational.Column" name="cancel_time" id="D971704C-E697-2D92-65AF-54677D11955D">
         <createdBy>xu_dengfeng</createdBy>
         <createdTime>2012-02-14 03:28:28 UTC</createdTime>
         <comment>取消医嘱的公元纪年日期和时间的完整描述</comment>
         <generatorID>DF9323E6-1025-7107-F82F-F8FACB37D842</generatorID>
         <ownerDesignName>CDR</ownerDesignName>
         <engineerTo>
            <item key="C569ACD5-9D32-D25B-CB96-FE071904E1B3" value="true"/>
         </engineerTo>
         <nullsAllowed>true</nullsAllowed>
         <use>1</use>
         <logicalDatatype>LOGDT008</logicalDatatype>
         <previousColumn>false</previousColumn>
         <autoIncrementCycle>false</autoIncrementCycle>
      </Column>
      <Column class="oracle.dbtools.crest.model.design.relational.Column" name="order_dept" id="01D25812-1B5D-5EFB-B211-38A8087FF426">
         <createdBy>xu_dengfeng</createdBy>
         <createdTime>2012-02-14 03:28:28 UTC</createdTime>
         <comment>下达医嘱的科室描述</comment>
         <generatorID>EC60CC5C-CE0B-8863-A6F8-05A60ED5065D</generatorID>
         <ownerDesignName>CDR</ownerDesignName>
         <engineerTo>
            <item key="C569ACD5-9D32-D25B-CB96-FE071904E1B3" value="true"/>
         </engineerTo>
         <nullsAllowed>true</nullsAllowed>
         <use>1</use>
         <logicalDatatype>LOGDT008</logicalDatatype>
         <previousColumn>false</previousColumn>
         <autoIncrementCycle>false</autoIncrementCycle>
      </Column>
      <Column class="oracle.dbtools.crest.model.design.relational.Column" name="order_person" id="EA541795-3DF6-17EB-D1C2-3029464A5E1A">
         <createdBy>xu_dengfeng</createdBy>
         <createdTime>2012-02-14 03:28:28 UTC</createdTime>
         <comment>下达医嘱的医务人员描述，一般是护士</comment>
         <generatorID>A09B6854-B3AC-0283-CA65-BBF34B401E77</generatorID>
         <ownerDesignName>CDR</ownerDesignName>
         <engineerTo>
            <item key="C569ACD5-9D32-D25B-CB96-FE071904E1B3" value="true"/>
         </engineerTo>
         <nullsAllowed>true</nullsAllowed>
         <use>1</use>
         <logicalDatatype>LOGDT011</logicalDatatype>
         <previousColumn>false</previousColumn>
         <autoIncrementCycle>false</autoIncrementCycle>
      </Column>
      <Column class="oracle.dbtools.crest.model.design.relational.Column" name="confirm_person" id="5A02AADB-8080-90D4-C5E3-C73A123D5A78">
         <createdBy>xu_dengfeng</createdBy>
         <createdTime>2012-02-14 03:28:28 UTC</createdTime>
         <comment>对医嘱进行确认的医务人员描述，一般是护士</comment>
         <generatorID>D7DBD10E-F447-8A78-B16F-3CF9DF5F8290</generatorID>
         <ownerDesignName>CDR</ownerDesignName>
         <engineerTo>
            <item key="C569ACD5-9D32-D25B-CB96-FE071904E1B3" value="true"/>
         </engineerTo>
         <nullsAllowed>true</nullsAllowed>
         <use>1</use>
         <logicalDatatype>LOGDT011</logicalDatatype>
         <previousColumn>false</previousColumn>
         <autoIncrementCycle>false</autoIncrementCycle>
      </Column>
      <Column class="oracle.dbtools.crest.model.design.relational.Column" name="execution_frequency" id="113D2E96-C904-8F02-DCCD-8AE33C792CBC">
         <createdBy>xu_dengfeng</createdBy>
         <createdTime>2012-02-14 03:28:28 UTC</createdTime>
         <comment>医嘱的执行频率，一般为一次(ONCE)</comment>
         <generatorID>7B2815E2-D192-5484-3117-322B84554812</generatorID>
         <ownerDesignName>CDR</ownerDesignName>
         <engineerTo>
            <item key="C569ACD5-9D32-D25B-CB96-FE071904E1B3" value="true"/>
         </engineerTo>
         <nullsAllowed>true</nullsAllowed>
         <use>1</use>
         <logicalDatatype>LOGDT011</logicalDatatype>
         <previousColumn>false</previousColumn>
         <autoIncrementCycle>false</autoIncrementCycle>
      </Column>
      <Column class="oracle.dbtools.crest.model.design.relational.Column" name="from_dept" id="4730ADE2-277B-EB29-9175-D6C45B0FE200">
         <createdBy>xu_dengfeng</createdBy>
         <createdTime>2012-02-14 03:28:28 UTC</createdTime>
         <comment>转出科室的描述</comment>
         <generatorID>C708CD42-8054-C476-46E9-FB02899BF95B</generatorID>
         <ownerDesignName>CDR</ownerDesignName>
         <engineerTo>
            <item key="C569ACD5-9D32-D25B-CB96-FE071904E1B3" value="true"/>
         </engineerTo>
         <nullsAllowed>true</nullsAllowed>
         <use>1</use>
         <logicalDatatype>LOGDT011</logicalDatatype>
         <previousColumn>false</previousColumn>
         <autoIncrementCycle>false</autoIncrementCycle>
      </Column>
      <Column class="oracle.dbtools.crest.model.design.relational.Column" name="from_wards" id="7D0876FC-0561-9B4E-700C-6320F835E9A6">
         <createdBy>xu_dengfeng</createdBy>
         <createdTime>2012-02-14 03:28:28 UTC</createdTime>
         <comment>转出病区的描述</comment>
         <generatorID>67532D2B-F286-D1D8-9BA4-9A7AD3887232</generatorID>
         <ownerDesignName>CDR</ownerDesignName>
         <engineerTo>
            <item key="C569ACD5-9D32-D25B-CB96-FE071904E1B3" value="true"/>
         </engineerTo>
         <nullsAllowed>true</nullsAllowed>
         <use>1</use>
         <logicalDatatype>LOGDT011</logicalDatatype>
         <previousColumn>false</previousColumn>
         <autoIncrementCycle>false</autoIncrementCycle>
      </Column>
      <Column class="oracle.dbtools.crest.model.design.relational.Column" name="to_dept" id="932ABE8C-3013-09BE-B3CE-F9EBCBE1FD30">
         <createdBy>xu_dengfeng</createdBy>
         <createdTime>2012-02-14 03:28:28 UTC</createdTime>
         <comment>转入科室的描述</comment>
         <generatorID>1785EF04-30EF-11AC-5F3A-B839866E7A8B</generatorID>
         <ownerDesignName>CDR</ownerDesignName>
         <engineerTo>
            <item key="C569ACD5-9D32-D25B-CB96-FE071904E1B3" value="true"/>
         </engineerTo>
         <nullsAllowed>true</nullsAllowed>
         <use>1</use>
         <logicalDatatype>LOGDT011</logicalDatatype>
         <previousColumn>false</previousColumn>
         <autoIncrementCycle>false</autoIncrementCycle>
      </Column>
      <Column class="oracle.dbtools.crest.model.design.relational.Column" name="to_wards" id="1E23F400-C8B2-BE15-9D5B-5ED49DF27844">
         <createdBy>xu_dengfeng</createdBy>
         <createdTime>2012-02-14 03:28:28 UTC</createdTime>
         <comment>转入病区的描述</comment>
         <generatorID>209692B4-F9BE-1611-F186-F1446F56AE36</generatorID>
         <ownerDesignName>CDR</ownerDesignName>
         <engineerTo>
            <item key="C569ACD5-9D32-D25B-CB96-FE071904E1B3" value="true"/>
         </engineerTo>
         <nullsAllowed>true</nullsAllowed>
         <use>1</use>
         <logicalDatatype>LOGDT011</logicalDatatype>
         <previousColumn>false</previousColumn>
         <autoIncrementCycle>false</autoIncrementCycle>
      </Column>
      <Column class="oracle.dbtools.crest.model.design.relational.Column" name="destination" id="C4969EFB-0F4C-40F2-B98A-069AA2276EA7">
         <createdBy>xu_dengfeng</createdBy>
         <createdTime>2012-02-14 03:28:28 UTC</createdTime>
         <generatorID>270A775A-4BE8-5974-E820-CA9F579DC70C</generatorID>
         <ownerDesignName>CDR</ownerDesignName>
         <engineerTo>
            <item key="C569ACD5-9D32-D25B-CB96-FE071904E1B3" value="true"/>
         </engineerTo>
         <nullsAllowed>true</nullsAllowed>
         <use>1</use>
         <logicalDatatype>LOGDT024</logicalDatatype>
         <dataTypeSize>200</dataTypeSize>
         <previousColumn>false</previousColumn>
         <autoIncrementCycle>false</autoIncrementCycle>
      </Column>
      <Column class="oracle.dbtools.crest.model.design.relational.Column" name="create_time" id="16F56E5A-5EFC-A091-2883-87E86275F87F">
         <createdBy>xu_dengfeng</createdBy>
         <createdTime>2012-02-14 03:28:28 UTC</createdTime>
         <generatorID>41EEA948-F0FB-64FC-3C72-FC559D6D53E0</generatorID>
         <ownerDesignName>CDR</ownerDesignName>
         <engineerTo>
            <item key="C569ACD5-9D32-D25B-CB96-FE071904E1B3" value="true"/>
         </engineerTo>
         <use>1</use>
         <logicalDatatype>LOGDT008</logicalDatatype>
         <previousColumn>false</previousColumn>
         <autoIncrementCycle>false</autoIncrementCycle>
      </Column>
      <Column class="oracle.dbtools.crest.model.design.relational.Column" name="update_time" id="0A7C403C-267E-8F57-819F-32833A09D92D">
         <createdBy>xu_dengfeng</createdBy>
         <createdTime>2012-02-14 03:28:28 UTC</createdTime>
         <generatorID>06AFB87D-BFE8-4A8C-9ADB-541BAE78D6E3</generatorID>
         <ownerDesignName>CDR</ownerDesignName>
         <engineerTo>
            <item key="C569ACD5-9D32-D25B-CB96-FE071904E1B3" value="true"/>
         </engineerTo>
         <use>1</use>
         <logicalDatatype>LOGDT008</logicalDatatype>
         <previousColumn>false</previousColumn>
         <autoIncrementCycle>false</autoIncrementCycle>
      </Column>
      <Column class="oracle.dbtools.crest.model.design.relational.Column" name="update_count" id="F97E0542-F593-A049-0938-1FEA77BB1364">
         <createdBy>xu_dengfeng</createdBy>
         <createdTime>2012-02-14 03:28:28 UTC</createdTime>
         <generatorID>D3E02FC3-CE81-5656-9C64-F1AB48B59026</generatorID>
         <ownerDesignName>CDR</ownerDesignName>
         <engineerTo>
            <item key="C569ACD5-9D32-D25B-CB96-FE071904E1B3" value="true"/>
         </engineerTo>
         <use>1</use>
         <logicalDatatype>LOGDT011</logicalDatatype>
         <previousColumn>false</previousColumn>
         <autoIncrementCycle>false</autoIncrementCycle>
      </Column>
      <Column class="oracle.dbtools.crest.model.design.relational.Column" name="delete_flag" id="3462EEAA-A571-2F41-49E2-E3BB4C602BCC">
         <createdBy>xu_dengfeng</createdBy>
         <createdTime>2012-02-14 03:28:28 UTC</createdTime>
         <generatorID>E48FACEB-1049-BF82-1FA6-EC209FBFC8D9</generatorID>
         <ownerDesignName>CDR</ownerDesignName>
         <engineerTo>
            <item key="C569ACD5-9D32-D25B-CB96-FE071904E1B3" value="true"/>
         </engineerTo>
         <use>1</use>
         <logicalDatatype>LOGDT006</logicalDatatype>
         <dataTypeSize>1</dataTypeSize>
         <previousColumn>false</previousColumn>
         <autoIncrementCycle>false</autoIncrementCycle>
      </Column>
      <Column class="oracle.dbtools.crest.model.design.relational.Column" name="delete_time" id="4BA9AE6A-8894-2E5D-736B-67F0871D65D8">
         <createdBy>xu_dengfeng</createdBy>
         <createdTime>2012-02-14 03:28:28 UTC</createdTime>
         <generatorID>39D647C8-3960-53D9-57A1-75DAB93E6CC2</generatorID>
         <ownerDesignName>CDR</ownerDesignName>
         <engineerTo>
            <item key="C569ACD5-9D32-D25B-CB96-FE071904E1B3" value="true"/>
         </engineerTo>
         <nullsAllowed>true</nullsAllowed>
         <use>1</use>
         <logicalDatatype>LOGDT008</logicalDatatype>
         <previousColumn>false</previousColumn>
         <autoIncrementCycle>false</autoIncrementCycle>
      </Column>
   </columns>
   <indexes>
      <ind_PK_UK class="oracle.dbtools.crest.model.design.relational.Index" id="1E383BA1-FCF6-38B5-C5DB-B0A4B2384367" name="pk_transfer_history">
         <createdBy>xu_dengfeng</createdBy>
         <createdTime>2012-02-14 03:28:28 UTC</createdTime>
         <generatorID>D7785D2F-9E9E-6633-519E-E8C02DCA6E99</generatorID>
         <ownerDesignName>CDR</ownerDesignName>
         <engineerTo>
            <item key="C569ACD5-9D32-D25B-CB96-FE071904E1B3" value="true"/>
         </engineerTo>
         <pk>true</pk>
         <indexState>Primary Constraint</indexState>
         <indexColumnUsage>
            <colUsage columnID="083EE24F-9894-D5E7-E2DC-CE9E52386E2D"/>
         </indexColumnUsage>
      </ind_PK_UK>
      <ind_PK_UK class="oracle.dbtools.crest.model.design.relational.Index" id="DABA31EC-2A52-A237-3606-18C90CF3BA3A" name="fk_visit_transfer">
         <createdBy>xu_dengfeng</createdBy>
         <createdTime>2012-02-14 03:28:28 UTC</createdTime>
         <generatorID>4139EA1E-F6AE-BC60-697D-04F4301EF8C6</generatorID>
         <ownerDesignName>CDR</ownerDesignName>
         <engineerTo>
            <item key="C569ACD5-9D32-D25B-CB96-FE071904E1B3" value="true"/>
         </engineerTo>
         <indexColumnUsage>
            <colUsage columnID="568FACA2-BF86-CDBD-5FB1-1B45D1F8367B"/>
         </indexColumnUsage>
      </ind_PK_UK>
   </indexes>
</Table>