<?xml version = '1.0' encoding = 'UTF-8'?>
<Table class="oracle.dbtools.crest.model.design.relational.Table" id="ABE29FD4-EB49-CD41-AF54-3ACD32C88281" directorySegmentName="seg_0" name="social_insurance">
   <createdBy>xu_dengfeng</createdBy>
   <createdTime>2012-02-14 03:28:28 UTC</createdTime>
   <generatorID>D578F079-57E4-F431-6597-36C00C9DCE13</generatorID>
   <ownerDesignName>CDR</ownerDesignName>
   <engineerTo>
      <item key="C569ACD5-9D32-D25B-CB96-FE071904E1B3" value="true"/>
   </engineerTo>
   <pkName>pk_social_insurance</pkName>
   <fonts>
      <FontObject class="oracle.dbtools.crest.model.design.FontObjectWr">
         <foType>标题</foType>
         <fontStyle>1</fontStyle>
         <colorRGB>-16776961</colorRGB>
      </FontObject>
      <FontObject class="oracle.dbtools.crest.model.design.FontObjectWr">
         <foType>列</foType>
         <colorRGB>-16777216</colorRGB>
      </FontObject>
      <FontObject class="oracle.dbtools.crest.model.design.FontObjectWr">
         <foType>数据类型</foType>
         <colorRGB>-16744448</colorRGB>
      </FontObject>
      <FontObject class="oracle.dbtools.crest.model.design.FontObjectWr">
         <foType>PK 元素</foType>
         <colorRGB>-16776961</colorRGB>
      </FontObject>
      <FontObject class="oracle.dbtools.crest.model.design.FontObjectWr">
         <foType>FK 元素</foType>
         <colorRGB>-16777216</colorRGB>
      </FontObject>
      <FontObject class="oracle.dbtools.crest.model.design.FontObjectWr">
         <foType>UK 元素</foType>
         <colorRGB>-16776961</colorRGB>
      </FontObject>
      <FontObject class="oracle.dbtools.crest.model.design.FontObjectWr">
         <foType>非空值</foType>
         <colorRGB>-65536</colorRGB>
      </FontObject>
      <FontObject class="oracle.dbtools.crest.model.design.FontObjectWr">
         <foType>关键字</foType>
         <colorRGB>-16777216</colorRGB>
      </FontObject>
   </fonts>
   <columns>
      <Column class="oracle.dbtools.crest.model.design.relational.Column" name="patient_sn" id="E8B51A57-747E-AB35-F992-623133FE0F3B">
         <createdBy>xu_dengfeng</createdBy>
         <createdTime>2012-02-14 03:28:28 UTC</createdTime>
         <generatorID>2A6820BD-B191-937C-BA76-3DE0A7D81991</generatorID>
         <ownerDesignName>CDR</ownerDesignName>
         <engineerTo>
            <item key="C569ACD5-9D32-D25B-CB96-FE071904E1B3" value="true"/>
         </engineerTo>
         <use>1</use>
         <logicalDatatype>LOGDT024</logicalDatatype>
         <dataTypeSize>32</dataTypeSize>
         <delegate>01A99A33-2296-FFFB-3B09-ADF407D3AC92</delegate>
         <previousColumn>false</previousColumn>
         <autoIncrementCycle>false</autoIncrementCycle>
         <associations>
            <colAssociation fkAssociation="814A7E76-A52F-526E-3DC4-551A71FCD403" referredColumn="01A99A33-2296-FFFB-3B09-ADF407D3AC92"/>
         </associations>
      </Column>
      <Column class="oracle.dbtools.crest.model.design.relational.Column" name="card_no" id="F671E13B-0EE6-4428-403D-B16FCBA8E971">
         <createdBy>xu_dengfeng</createdBy>
         <createdTime>2012-02-14 03:28:28 UTC</createdTime>
         <generatorID>3D3F39E3-13D0-19DB-9BE7-BF10CE965EB2</generatorID>
         <ownerDesignName>CDR</ownerDesignName>
         <engineerTo>
            <item key="C569ACD5-9D32-D25B-CB96-FE071904E1B3" value="true"/>
         </engineerTo>
         <use>1</use>
         <logicalDatatype>LOGDT024</logicalDatatype>
         <dataTypeSize>20</dataTypeSize>
         <previousColumn>false</previousColumn>
         <autoIncrementCycle>false</autoIncrementCycle>
      </Column>
      <Column class="oracle.dbtools.crest.model.design.relational.Column" name="ic_no" id="93261E23-C50A-F474-BE17-C848D648CD0F">
         <createdBy>xu_dengfeng</createdBy>
         <createdTime>2012-02-14 03:28:28 UTC</createdTime>
         <generatorID>5F7F9D47-ADF9-623A-169E-E5559DF7179F</generatorID>
         <ownerDesignName>CDR</ownerDesignName>
         <engineerTo>
            <item key="C569ACD5-9D32-D25B-CB96-FE071904E1B3" value="true"/>
         </engineerTo>
         <use>1</use>
         <logicalDatatype>LOGDT024</logicalDatatype>
         <dataTypeSize>20</dataTypeSize>
         <previousColumn>false</previousColumn>
         <autoIncrementCycle>false</autoIncrementCycle>
      </Column>
      <Column class="oracle.dbtools.crest.model.design.relational.Column" name="id_no" id="A7AAFD0B-49C1-EE6F-842E-05A0083B95AC">
         <createdBy>xu_dengfeng</createdBy>
         <createdTime>2012-02-14 03:28:28 UTC</createdTime>
         <generatorID>1C3BB940-E346-0B89-6E9D-6D8B1E6D0A7D</generatorID>
         <ownerDesignName>CDR</ownerDesignName>
         <engineerTo>
            <item key="C569ACD5-9D32-D25B-CB96-FE071904E1B3" value="true"/>
         </engineerTo>
         <nullsAllowed>true</nullsAllowed>
         <use>1</use>
         <logicalDatatype>LOGDT024</logicalDatatype>
         <dataTypeSize>18</dataTypeSize>
         <previousColumn>false</previousColumn>
         <autoIncrementCycle>false</autoIncrementCycle>
      </Column>
      <Column class="oracle.dbtools.crest.model.design.relational.Column" name="personname" id="D55635E3-0E9C-D417-424E-0680033AB01E">
         <createdBy>xu_dengfeng</createdBy>
         <createdTime>2012-02-14 03:28:28 UTC</createdTime>
         <generatorID>3E4B7DC9-A629-2395-8D1B-744906F495BC</generatorID>
         <ownerDesignName>CDR</ownerDesignName>
         <engineerTo>
            <item key="C569ACD5-9D32-D25B-CB96-FE071904E1B3" value="true"/>
         </engineerTo>
         <nullsAllowed>true</nullsAllowed>
         <use>1</use>
         <logicalDatatype>LOGDT024</logicalDatatype>
         <dataTypeSize>20</dataTypeSize>
         <previousColumn>false</previousColumn>
         <autoIncrementCycle>false</autoIncrementCycle>
      </Column>
      <Column class="oracle.dbtools.crest.model.design.relational.Column" name="sex" id="54087258-9366-805C-C972-AA722C8EE172">
         <createdBy>xu_dengfeng</createdBy>
         <createdTime>2012-02-14 03:28:28 UTC</createdTime>
         <generatorID>5D55F122-435F-8A38-F73B-AB676E2F4FF4</generatorID>
         <ownerDesignName>CDR</ownerDesignName>
         <engineerTo>
            <item key="C569ACD5-9D32-D25B-CB96-FE071904E1B3" value="true"/>
         </engineerTo>
         <nullsAllowed>true</nullsAllowed>
         <use>1</use>
         <logicalDatatype>LOGDT024</logicalDatatype>
         <dataTypeSize>6</dataTypeSize>
         <previousColumn>false</previousColumn>
         <autoIncrementCycle>false</autoIncrementCycle>
      </Column>
      <Column class="oracle.dbtools.crest.model.design.relational.Column" name="birthday" id="AFF5181A-7BF5-1CDD-A347-9863FA44EC88">
         <createdBy>xu_dengfeng</createdBy>
         <createdTime>2012-02-14 03:28:28 UTC</createdTime>
         <generatorID>8FA29255-62B1-B44A-ACBB-B780493543EC</generatorID>
         <ownerDesignName>CDR</ownerDesignName>
         <engineerTo>
            <item key="C569ACD5-9D32-D25B-CB96-FE071904E1B3" value="true"/>
         </engineerTo>
         <nullsAllowed>true</nullsAllowed>
         <use>1</use>
         <logicalDatatype>LOGDT008</logicalDatatype>
         <previousColumn>false</previousColumn>
         <autoIncrementCycle>false</autoIncrementCycle>
      </Column>
      <Column class="oracle.dbtools.crest.model.design.relational.Column" name="fromhosp" id="9723AD10-98FA-C22A-C81F-D683E0F8C3BB">
         <createdBy>xu_dengfeng</createdBy>
         <createdTime>2012-02-14 03:28:28 UTC</createdTime>
         <generatorID>E4C284FB-EBF8-10CF-D39C-37D2241F9FC3</generatorID>
         <ownerDesignName>CDR</ownerDesignName>
         <engineerTo>
            <item key="C569ACD5-9D32-D25B-CB96-FE071904E1B3" value="true"/>
         </engineerTo>
         <nullsAllowed>true</nullsAllowed>
         <use>1</use>
         <logicalDatatype>LOGDT024</logicalDatatype>
         <dataTypeSize>8</dataTypeSize>
         <previousColumn>false</previousColumn>
         <autoIncrementCycle>false</autoIncrementCycle>
      </Column>
      <Column class="oracle.dbtools.crest.model.design.relational.Column" name="fromhospdate" id="02D155F7-61A3-FDA5-2C33-B53412620277">
         <createdBy>xu_dengfeng</createdBy>
         <createdTime>2012-02-14 03:28:28 UTC</createdTime>
         <generatorID>EE744EE9-7179-A1C6-2483-DE7C83EEEDBF</generatorID>
         <ownerDesignName>CDR</ownerDesignName>
         <engineerTo>
            <item key="C569ACD5-9D32-D25B-CB96-FE071904E1B3" value="true"/>
         </engineerTo>
         <nullsAllowed>true</nullsAllowed>
         <use>1</use>
         <logicalDatatype>LOGDT008</logicalDatatype>
         <previousColumn>false</previousColumn>
         <autoIncrementCycle>false</autoIncrementCycle>
      </Column>
      <Column class="oracle.dbtools.crest.model.design.relational.Column" name="fundtype" id="509E92F3-9AE6-48E9-9129-64DFF4F61072">
         <createdBy>xu_dengfeng</createdBy>
         <createdTime>2012-02-14 03:28:28 UTC</createdTime>
         <generatorID>35EA9812-14FC-29C0-0ED1-BC393DE7A4BC</generatorID>
         <ownerDesignName>CDR</ownerDesignName>
         <engineerTo>
            <item key="C569ACD5-9D32-D25B-CB96-FE071904E1B3" value="true"/>
         </engineerTo>
         <nullsAllowed>true</nullsAllowed>
         <use>1</use>
         <logicalDatatype>LOGDT024</logicalDatatype>
         <dataTypeSize>4</dataTypeSize>
         <previousColumn>false</previousColumn>
         <autoIncrementCycle>false</autoIncrementCycle>
      </Column>
      <Column class="oracle.dbtools.crest.model.design.relational.Column" name="isyt" id="F17A691B-92F9-33A9-CE73-DFFB66DE392B">
         <createdBy>xu_dengfeng</createdBy>
         <createdTime>2012-02-14 03:28:28 UTC</createdTime>
         <generatorID>BD9B9E90-B426-5B13-71DB-9006B33E8F26</generatorID>
         <ownerDesignName>CDR</ownerDesignName>
         <engineerTo>
            <item key="C569ACD5-9D32-D25B-CB96-FE071904E1B3" value="true"/>
         </engineerTo>
         <nullsAllowed>true</nullsAllowed>
         <use>1</use>
         <logicalDatatype>LOGDT011</logicalDatatype>
         <previousColumn>false</previousColumn>
         <autoIncrementCycle>false</autoIncrementCycle>
      </Column>
      <Column class="oracle.dbtools.crest.model.design.relational.Column" name="jclevel" id="21B86DF8-CAC9-EC4B-9537-F570523A9E87">
         <createdBy>xu_dengfeng</createdBy>
         <createdTime>2012-02-14 03:28:28 UTC</createdTime>
         <generatorID>ADDF2781-5775-5403-CB0F-EFD5A2E913EB</generatorID>
         <ownerDesignName>CDR</ownerDesignName>
         <engineerTo>
            <item key="C569ACD5-9D32-D25B-CB96-FE071904E1B3" value="true"/>
         </engineerTo>
         <nullsAllowed>true</nullsAllowed>
         <use>1</use>
         <logicalDatatype>LOGDT011</logicalDatatype>
         <previousColumn>false</previousColumn>
         <autoIncrementCycle>false</autoIncrementCycle>
      </Column>
      <Column class="oracle.dbtools.crest.model.design.relational.Column" name="hospflag" id="4F503140-DFE7-2786-3CB1-6110C2702226">
         <createdBy>xu_dengfeng</createdBy>
         <createdTime>2012-02-14 03:28:28 UTC</createdTime>
         <generatorID>9399C60D-DAC9-B4CF-C82D-03EBC1084105</generatorID>
         <ownerDesignName>CDR</ownerDesignName>
         <engineerTo>
            <item key="C569ACD5-9D32-D25B-CB96-FE071904E1B3" value="true"/>
         </engineerTo>
         <nullsAllowed>true</nullsAllowed>
         <use>1</use>
         <logicalDatatype>LOGDT011</logicalDatatype>
         <previousColumn>false</previousColumn>
         <autoIncrementCycle>false</autoIncrementCycle>
      </Column>
      <Column class="oracle.dbtools.crest.model.design.relational.Column" name="persontype" id="6A33FC39-9690-0ABB-4FC4-218BE7AAC12E">
         <createdBy>xu_dengfeng</createdBy>
         <createdTime>2012-02-14 03:28:28 UTC</createdTime>
         <generatorID>19E5BACC-4377-6CFC-1420-CB801E4C1B77</generatorID>
         <ownerDesignName>CDR</ownerDesignName>
         <engineerTo>
            <item key="C569ACD5-9D32-D25B-CB96-FE071904E1B3" value="true"/>
         </engineerTo>
         <nullsAllowed>true</nullsAllowed>
         <use>1</use>
         <logicalDatatype>LOGDT024</logicalDatatype>
         <dataTypeSize>3</dataTypeSize>
         <previousColumn>false</previousColumn>
         <autoIncrementCycle>false</autoIncrementCycle>
      </Column>
      <Column class="oracle.dbtools.crest.model.design.relational.Column" name="isinredlist" id="7E9FC9D6-D71D-4C26-B140-28D517450A19">
         <createdBy>xu_dengfeng</createdBy>
         <createdTime>2012-02-14 03:28:28 UTC</createdTime>
         <generatorID>AE706DE7-F8A2-196F-EAFE-72A9B65641F2</generatorID>
         <ownerDesignName>CDR</ownerDesignName>
         <engineerTo>
            <item key="C569ACD5-9D32-D25B-CB96-FE071904E1B3" value="true"/>
         </engineerTo>
         <nullsAllowed>true</nullsAllowed>
         <use>1</use>
         <logicalDatatype>LOGDT024</logicalDatatype>
         <dataTypeSize>5</dataTypeSize>
         <previousColumn>false</previousColumn>
         <autoIncrementCycle>false</autoIncrementCycle>
      </Column>
      <Column class="oracle.dbtools.crest.model.design.relational.Column" name="isspecifiedhosp" id="519F9580-0DCD-BBD3-B861-B96BB1544963">
         <createdBy>xu_dengfeng</createdBy>
         <createdTime>2012-02-14 03:28:28 UTC</createdTime>
         <generatorID>11C89A34-15D4-6F2F-E709-71FE6F083A0F</generatorID>
         <ownerDesignName>CDR</ownerDesignName>
         <engineerTo>
            <item key="C569ACD5-9D32-D25B-CB96-FE071904E1B3" value="true"/>
         </engineerTo>
         <nullsAllowed>true</nullsAllowed>
         <use>1</use>
         <logicalDatatype>LOGDT024</logicalDatatype>
         <dataTypeSize>1</dataTypeSize>
         <previousColumn>false</previousColumn>
         <autoIncrementCycle>false</autoIncrementCycle>
      </Column>
      <Column class="oracle.dbtools.crest.model.design.relational.Column" name="ischronichosp" id="E3039D24-AEED-52EB-00D4-78F0C0EE5F4C">
         <createdBy>xu_dengfeng</createdBy>
         <createdTime>2012-02-14 03:28:28 UTC</createdTime>
         <generatorID>6E7F25C0-CBC3-2DB8-A732-6B8050665BCE</generatorID>
         <ownerDesignName>CDR</ownerDesignName>
         <engineerTo>
            <item key="C569ACD5-9D32-D25B-CB96-FE071904E1B3" value="true"/>
         </engineerTo>
         <nullsAllowed>true</nullsAllowed>
         <use>1</use>
         <logicalDatatype>LOGDT024</logicalDatatype>
         <dataTypeSize>5</dataTypeSize>
         <previousColumn>false</previousColumn>
         <autoIncrementCycle>false</autoIncrementCycle>
      </Column>
      <Column class="oracle.dbtools.crest.model.design.relational.Column" name="personcount" id="09892F9A-6055-0A44-F71A-4A3DFCA4AB85">
         <createdBy>xu_dengfeng</createdBy>
         <createdTime>2012-02-14 03:28:28 UTC</createdTime>
         <generatorID>0AE37D0E-1081-0E15-DEA6-A15C3C0A837B</generatorID>
         <ownerDesignName>CDR</ownerDesignName>
         <engineerTo>
            <item key="C569ACD5-9D32-D25B-CB96-FE071904E1B3" value="true"/>
         </engineerTo>
         <nullsAllowed>true</nullsAllowed>
         <use>1</use>
         <logicalDatatype>LOGDT019</logicalDatatype>
         <dataTypePrecision>10</dataTypePrecision>
         <dataTypeScale>2</dataTypeScale>
         <previousColumn>false</previousColumn>
         <autoIncrementCycle>false</autoIncrementCycle>
      </Column>
      <Column class="oracle.dbtools.crest.model.design.relational.Column" name="chroniccode" id="3486FA8E-324E-056D-0F5B-AA35A7B941D1">
         <createdBy>xu_dengfeng</createdBy>
         <createdTime>2012-02-14 03:28:28 UTC</createdTime>
         <generatorID>0AE55E5B-FEC1-3BFD-81B1-081A251AC637</generatorID>
         <ownerDesignName>CDR</ownerDesignName>
         <engineerTo>
            <item key="C569ACD5-9D32-D25B-CB96-FE071904E1B3" value="true"/>
         </engineerTo>
         <nullsAllowed>true</nullsAllowed>
         <use>1</use>
         <logicalDatatype>LOGDT024</logicalDatatype>
         <dataTypeSize>50</dataTypeSize>
         <previousColumn>false</previousColumn>
         <autoIncrementCycle>false</autoIncrementCycle>
      </Column>
      <Column class="oracle.dbtools.crest.model.design.relational.Column" name="create_time" id="0E78F849-35F3-083B-5D41-0DA066A2B728">
         <createdBy>xu_dengfeng</createdBy>
         <createdTime>2012-02-14 03:28:28 UTC</createdTime>
         <generatorID>932E990F-3820-ECEC-80F1-C52F15528591</generatorID>
         <ownerDesignName>CDR</ownerDesignName>
         <engineerTo>
            <item key="C569ACD5-9D32-D25B-CB96-FE071904E1B3" value="true"/>
         </engineerTo>
         <use>1</use>
         <logicalDatatype>LOGDT008</logicalDatatype>
         <previousColumn>false</previousColumn>
         <autoIncrementCycle>false</autoIncrementCycle>
      </Column>
      <Column class="oracle.dbtools.crest.model.design.relational.Column" name="update_time" id="BB19D6B8-2294-DA14-A13C-32AD93754B6B">
         <createdBy>xu_dengfeng</createdBy>
         <createdTime>2012-02-14 03:28:28 UTC</createdTime>
         <generatorID>02F60900-059A-A78E-7CA1-39A707F41A9F</generatorID>
         <ownerDesignName>CDR</ownerDesignName>
         <engineerTo>
            <item key="C569ACD5-9D32-D25B-CB96-FE071904E1B3" value="true"/>
         </engineerTo>
         <use>1</use>
         <logicalDatatype>LOGDT008</logicalDatatype>
         <previousColumn>false</previousColumn>
         <autoIncrementCycle>false</autoIncrementCycle>
      </Column>
      <Column class="oracle.dbtools.crest.model.design.relational.Column" name="update_count" id="B73F19CA-5806-38B5-7F29-E7D9A9A5EAB9">
         <createdBy>xu_dengfeng</createdBy>
         <createdTime>2012-02-14 03:28:28 UTC</createdTime>
         <generatorID>C1DAFA23-0EB5-BE53-0489-0E513DF037BF</generatorID>
         <ownerDesignName>CDR</ownerDesignName>
         <engineerTo>
            <item key="C569ACD5-9D32-D25B-CB96-FE071904E1B3" value="true"/>
         </engineerTo>
         <use>1</use>
         <logicalDatatype>LOGDT011</logicalDatatype>
         <previousColumn>false</previousColumn>
         <autoIncrementCycle>false</autoIncrementCycle>
      </Column>
      <Column class="oracle.dbtools.crest.model.design.relational.Column" name="delete_flag" id="09DDB5A4-B893-9E14-ED7F-3B3A39DEF87F">
         <createdBy>xu_dengfeng</createdBy>
         <createdTime>2012-02-14 03:28:28 UTC</createdTime>
         <generatorID>276E46D5-EEB8-6668-21ED-57A0E1609C27</generatorID>
         <ownerDesignName>CDR</ownerDesignName>
         <engineerTo>
            <item key="C569ACD5-9D32-D25B-CB96-FE071904E1B3" value="true"/>
         </engineerTo>
         <use>1</use>
         <logicalDatatype>LOGDT006</logicalDatatype>
         <dataTypeSize>1</dataTypeSize>
         <previousColumn>false</previousColumn>
         <autoIncrementCycle>false</autoIncrementCycle>
      </Column>
      <Column class="oracle.dbtools.crest.model.design.relational.Column" name="delete_time" id="0692A909-0C0B-BCE9-D385-0846A2261F5E">
         <createdBy>xu_dengfeng</createdBy>
         <createdTime>2012-02-14 03:28:28 UTC</createdTime>
         <generatorID>71194D77-87DB-7254-9499-649A3004B190</generatorID>
         <ownerDesignName>CDR</ownerDesignName>
         <engineerTo>
            <item key="C569ACD5-9D32-D25B-CB96-FE071904E1B3" value="true"/>
         </engineerTo>
         <nullsAllowed>true</nullsAllowed>
         <use>1</use>
         <logicalDatatype>LOGDT008</logicalDatatype>
         <previousColumn>false</previousColumn>
         <autoIncrementCycle>false</autoIncrementCycle>
      </Column>
   </columns>
   <indexes>
      <ind_PK_UK class="oracle.dbtools.crest.model.design.relational.Index" id="DB82E5B5-39F3-0BE7-A660-F8562019BDA2" name="pk_social_insurance">
         <createdBy>xu_dengfeng</createdBy>
         <createdTime>2012-02-14 03:28:28 UTC</createdTime>
         <generatorID>2750ECF9-2582-7D21-C418-0A2BCF663A3C</generatorID>
         <ownerDesignName>CDR</ownerDesignName>
         <engineerTo>
            <item key="C569ACD5-9D32-D25B-CB96-FE071904E1B3" value="true"/>
         </engineerTo>
         <pk>true</pk>
         <indexState>Primary Constraint</indexState>
         <indexColumnUsage>
            <colUsage columnID="E8B51A57-747E-AB35-F992-623133FE0F3B"/>
         </indexColumnUsage>
      </ind_PK_UK>
      <ind_PK_UK class="oracle.dbtools.crest.model.design.relational.Index" id="E75A74FF-F39F-5145-DAB8-822E8513AE8B" name="fk_patient_insure">
         <createdBy>xu_dengfeng</createdBy>
         <createdTime>2012-02-14 03:28:28 UTC</createdTime>
         <generatorID>D2FBA36B-3B44-5993-9209-BCA3956D76F9</generatorID>
         <ownerDesignName>CDR</ownerDesignName>
         <engineerTo>
            <item key="C569ACD5-9D32-D25B-CB96-FE071904E1B3" value="true"/>
         </engineerTo>
         <indexColumnUsage>
            <colUsage columnID="E8B51A57-747E-AB35-F992-623133FE0F3B"/>
         </indexColumnUsage>
      </ind_PK_UK>
   </indexes>
</Table>