<?xml version = '1.0' encoding = 'UTF-8'?>
<Diagram class="oracle.dbtools.crest.swingui.relational.DPVRelationalSubView" name="From_LM_05.手术信息模型" id="AAEC2D2E-0686-2A2E-0EC4-B1C1A50D226F">
   <createdBy>xu_dengfeng</createdBy>
   <createdTime>2012-02-14 03:28:28 UTC</createdTime>
   <autoRoute>false</autoRoute>
   <boxInbox>true</boxInbox>
   <showLegend>false</showLegend>
   <showLabels>false</showLabels>
   <showGrid>false</showGrid>
   <diagramColor>-1</diagramColor>
   <display>false</display>
   <generatorId>817A021C-C1EB-0A6F-3E2A-79E80B624D66</generatorId>
   <notation>1</notation>
   <objectViews>
      <OView class="oracle.dbtools.crest.swingui.relational.TVTable" oid="08B5DA2D-B1EB-5EBC-A0E8-B4AD3158E145" otype="Table" vid="CAD89E4D-CA13-73D1-D87B-06D7678A539F">
         <bounds x="1015" y="1046" width="268" height="240"/>
         <generatorID>BACE0852-617C-BD7C-1240-93225B77F229</generatorID>
         <useDefaultColor>false</useDefaultColor>
         <backgroundColor>-3355393</backgroundColor>
         <foregroundColor>-16776961</foregroundColor>
      </OView>
      <OView class="oracle.dbtools.crest.swingui.relational.TVTable" oid="15EA725F-147B-0195-0942-DAB8CE6B621E" otype="Table" vid="E7A5A306-8E4A-64EA-A387-3A1266ED959C">
         <bounds x="359" y="808" width="235" height="420"/>
         <generatorID>4D16FF0A-0D01-D31B-F5CB-BF66BCB43FF6</generatorID>
      </OView>
      <OView class="oracle.dbtools.crest.swingui.relational.TVTable" oid="37BBCDBF-DCF4-8C1A-0D28-8DA23714EC5E" otype="Table" vid="820A7380-974C-9F47-3AF6-8F05338AE1AF">
         <bounds x="10" y="981" width="257" height="180"/>
         <generatorID>ED0495CB-0A42-31A4-1851-C2968FE5B791</generatorID>
      </OView>
      <OView class="oracle.dbtools.crest.swingui.relational.TVTable" oid="3943B02B-F556-998D-A67D-4716EC4F4371" otype="Table" vid="40D0D60A-F764-C4B1-1AF8-A7FA671AD249">
         <bounds x="920" y="4" width="247" height="405"/>
         <generatorID>2446B3FE-D696-05D0-392C-C4B3DF9F36AB</generatorID>
         <useDefaultColor>false</useDefaultColor>
         <backgroundColor>-3355393</backgroundColor>
         <foregroundColor>-16776961</foregroundColor>
      </OView>
      <OView class="oracle.dbtools.crest.swingui.relational.TVTable" oid="4B5D79BF-CE70-7CC1-E837-D71DDAD0B2AA" otype="Table" vid="01520C42-89DE-4E39-0A7D-9790603AFCFE">
         <bounds x="1015" y="808" width="249" height="225"/>
         <generatorID>87F45F9D-8078-60DF-42B4-797F652895C8</generatorID>
      </OView>
      <OView class="oracle.dbtools.crest.swingui.relational.TVTable" oid="4BA14DB8-79A2-674C-EA70-017D35F78A29" otype="Table" vid="B8CAFD02-016E-EABF-E781-8CF4FF8E9346">
         <bounds x="684" y="732" width="208" height="345"/>
         <generatorID>359D356B-E3FA-A5AA-1587-502CF063EC48</generatorID>
      </OView>
      <OView class="oracle.dbtools.crest.swingui.relational.TVTable" oid="661C3F8E-4766-8568-C077-31F20587547A" otype="Table" vid="BA3BAE6D-55F8-F91D-D25B-B346BFF368ED">
         <bounds x="535" y="34" width="225" height="607"/>
         <generatorID>543BDDE6-2C68-39B3-5133-550F55AB902D</generatorID>
         <useCustomFormat>true</useCustomFormat>
         <useDefaultColor>false</useDefaultColor>
         <backgroundColor>-3355393</backgroundColor>
         <foregroundColor>-16776961</foregroundColor>
      </OView>
      <OView class="oracle.dbtools.crest.swingui.relational.TVTable" oid="73114DEE-EB4D-F952-51CA-FB7C5CD04315" otype="Table" vid="28775CDF-C363-DD5A-B9F8-DD63978BB62D">
         <bounds x="1225" y="244" width="255" height="345"/>
         <generatorID>8B30A27F-BF10-7CED-6688-AF4534B5EC10</generatorID>
      </OView>
      <OView class="oracle.dbtools.crest.swingui.relational.TVTable" oid="9ED5994C-B642-24C8-0FA0-390B38BFD11E" otype="Table" vid="2D8CF787-A1E5-C878-470F-64FD83F8975C">
         <bounds x="922" y="424" width="220" height="375"/>
         <generatorID>04003C73-C007-4640-8296-E1841663196F</generatorID>
      </OView>
      <OView class="oracle.dbtools.crest.swingui.relational.TVTable" oid="C44348E4-2714-3E78-0C6B-11AC4EC3EA66" otype="Table" vid="FAD5A5A2-1C0F-6706-8B1C-95CE37FC58BA">
         <bounds x="40" y="568" width="203" height="390"/>
         <generatorID>86795F03-A7F9-C505-1E4A-8D01B4640A72</generatorID>
      </OView>
      <OView class="oracle.dbtools.crest.swingui.relational.TVTable" oid="EB7F3B59-0605-35B1-9422-08E2C0879D64" otype="Table" vid="C3D00419-4251-2004-4B42-B56B929C8851">
         <bounds x="150" y="14" width="225" height="495"/>
         <generatorID>3B2CF484-ACB1-6B2A-1D53-BDFC75A4B4F8</generatorID>
      </OView>
      <OView class="oracle.dbtools.crest.swingui.relational.TVTable" oid="FC9D5301-39D4-D4AC-E74C-07400E28DD60" otype="Table" vid="27120177-BC0A-5FAC-DE76-F80461125E42">
         <bounds x="689" y="1103" width="249" height="210"/>
         <generatorID>490C1267-CA00-213C-C02F-D3DAE456834E</generatorID>
      </OView>
   </objectViews>
   <connectors>
      <Connector class="oracle.dbtools.crest.swingui.relational.TVFKRelation" oid="3320A741-4E00-4B34-E849-9E619D5C2CE1" otype="FKIndexAssociation" vid_source="B8CAFD02-016E-EABF-E781-8CF4FF8E9346" vid_target="E7A5A306-8E4A-64EA-A387-3A1266ED959C">
         <lineWidth>1</lineWidth>
         <points>
            <point x="225" y="310"/>
            <point x="476" y="808"/>
         </points>
      </Connector>
      <Connector class="oracle.dbtools.crest.swingui.relational.TVFKRelation" oid="332A86DD-8BE4-7D90-F4FD-1EBAA3418B77" otype="FKIndexAssociation" vid_source="C3D00419-4251-2004-4B42-B56B929C8851" vid_target="FAD5A5A2-1C0F-6706-8B1C-95CE37FC58BA">
         <lineWidth>1</lineWidth>
         <points>
            <point x="342" y="509"/>
            <point x="342" y="540"/>
         </points>
      </Connector>
      <Connector class="oracle.dbtools.crest.swingui.relational.TVFKRelation" oid="51036814-790F-F9B7-8727-D61B86D7CCFB" otype="FKIndexAssociation" vid_source="BA3BAE6D-55F8-F91D-D25B-B346BFF368ED" vid_target="C3D00419-4251-2004-4B42-B56B929C8851">
         <lineWidth>1</lineWidth>
         <points>
            <point x="535" y="535"/>
            <point x="450" y="535"/>
         </points>
      </Connector>
      <Connector class="oracle.dbtools.crest.swingui.relational.TVFKRelation" oid="533CBA49-218B-6394-FEF3-3AF7509E3B24" otype="FKIndexAssociation" vid_source="FAD5A5A2-1C0F-6706-8B1C-95CE37FC58BA" vid_target="E7A5A306-8E4A-64EA-A387-3A1266ED959C">
         <lineWidth>1</lineWidth>
         <points>
            <point x="419" y="650"/>
            <point x="419" y="808"/>
         </points>
      </Connector>
      <Connector class="oracle.dbtools.crest.swingui.relational.TVFKRelation" oid="716FBF09-D571-F3C7-CB57-A737ADC53292" otype="FKIndexAssociation" vid_source="BA3BAE6D-55F8-F91D-D25B-B346BFF368ED" vid_target="B8CAFD02-016E-EABF-E781-8CF4FF8E9346">
         <lineWidth>1</lineWidth>
         <points>
            <point x="535" y="255"/>
            <point x="310" y="255"/>
         </points>
      </Connector>
      <Connector class="oracle.dbtools.crest.swingui.relational.TVFKRelation" oid="779481C1-4EC3-D4D3-9A26-818794434C10" otype="FKIndexAssociation" vid_source="BA3BAE6D-55F8-F91D-D25B-B346BFF368ED" vid_target="2D8CF787-A1E5-C878-470F-64FD83F8975C">
         <lineWidth>1</lineWidth>
         <points>
            <point x="535" y="195"/>
            <point x="280" y="195"/>
         </points>
      </Connector>
      <Connector class="oracle.dbtools.crest.swingui.relational.TVFKRelation" oid="79BBBCCF-EE52-AC67-207D-C664AE1A902B" otype="FKIndexAssociation" vid_source="2D8CF787-A1E5-C878-470F-64FD83F8975C" vid_target="28775CDF-C363-DD5A-B9F8-DD63978BB62D">
         <lineWidth>1</lineWidth>
         <points>
            <point x="280" y="247"/>
            <point x="1225" y="247"/>
         </points>
      </Connector>
      <Connector class="oracle.dbtools.crest.swingui.relational.TVFKRelation" oid="83C12AED-B71F-C09E-7D82-F057BE846BB5" otype="FKIndexAssociation" vid_source="BA3BAE6D-55F8-F91D-D25B-B346BFF368ED" vid_target="E7A5A306-8E4A-64EA-A387-3A1266ED959C">
         <lineWidth>1</lineWidth>
         <points>
            <point x="535" y="235"/>
            <point x="300" y="235"/>
         </points>
      </Connector>
      <Connector class="oracle.dbtools.crest.swingui.relational.TVFKRelation" oid="8C56D24C-2C33-30EB-1EBF-17F9F264F4B4" otype="FKIndexAssociation" vid_source="E7A5A306-8E4A-64EA-A387-3A1266ED959C" vid_target="27120177-BC0A-5FAC-DE76-F80461125E42">
         <lineWidth>1</lineWidth>
         <points>
            <point x="445" y="808"/>
            <point x="445" y="196"/>
         </points>
      </Connector>
      <Connector class="oracle.dbtools.crest.swingui.relational.TVFKRelation" oid="C26E8F97-21F1-84AA-8BE8-F247CD3767E1" otype="FKIndexAssociation" vid_source="FAD5A5A2-1C0F-6706-8B1C-95CE37FC58BA" vid_target="C3D00419-4251-2004-4B42-B56B929C8851">
         <lineWidth>1</lineWidth>
         <points>
            <point x="352" y="540"/>
            <point x="352" y="509"/>
         </points>
      </Connector>
      <Connector class="oracle.dbtools.crest.swingui.relational.TVFKRelation" oid="C6B8C4B7-CC18-B7D9-0DCC-A01D8F67E683" otype="FKIndexAssociation" vid_source="BA3BAE6D-55F8-F91D-D25B-B346BFF368ED" vid_target="40D0D60A-F764-C4B1-1AF8-A7FA671AD249">
         <lineWidth>1</lineWidth>
         <points>
            <point x="535" y="455"/>
            <point x="410" y="455"/>
         </points>
      </Connector>
      <Connector class="oracle.dbtools.crest.swingui.relational.TVFKRelation" oid="D617B051-810F-8A6E-E336-528D9BCF4CC6" otype="FKIndexAssociation" vid_source="BA3BAE6D-55F8-F91D-D25B-B346BFF368ED" vid_target="FAD5A5A2-1C0F-6706-8B1C-95CE37FC58BA">
         <lineWidth>1</lineWidth>
         <points>
            <point x="535" y="590"/>
            <point x="480" y="590"/>
         </points>
      </Connector>
      <Connector class="oracle.dbtools.crest.swingui.relational.TVFKRelation" oid="EC28148E-3147-3670-2461-E23B0DEAB0E0" otype="FKIndexAssociation" vid_source="B8CAFD02-016E-EABF-E781-8CF4FF8E9346" vid_target="CAD89E4D-CA13-73D1-D87B-06D7678A539F">
         <lineWidth>1</lineWidth>
         <points>
            <point x="225" y="310"/>
            <point x="1149" y="1046"/>
         </points>
      </Connector>
      <Connector class="oracle.dbtools.crest.swingui.relational.TVFKRelation" oid="EDD39B69-01DA-7753-C4A5-073420A2B2D9" otype="FKIndexAssociation" vid_source="B8CAFD02-016E-EABF-E781-8CF4FF8E9346" vid_target="01520C42-89DE-4E39-0A7D-9790603AFCFE">
         <lineWidth>1</lineWidth>
         <points>
            <point x="684" y="904"/>
            <point x="345" y="550"/>
         </points>
      </Connector>
      <Connector class="oracle.dbtools.crest.swingui.relational.TVFKRelation" oid="EF205235-949E-D7D5-1AE0-DD9840814D4C" otype="FKIndexAssociation" vid_source="E7A5A306-8E4A-64EA-A387-3A1266ED959C" vid_target="820A7380-974C-9F47-3AF6-8F05338AE1AF">
         <lineWidth>1</lineWidth>
         <points>
            <point x="476" y="808"/>
            <point x="165" y="190"/>
         </points>
      </Connector>
   </connectors>
</Diagram>